xvirt/__init__.py
xvirt/collectors.py
xvirt/events.py
xvirt/newhooks.py
xvirt/plugin.py
xvirt/plugin_remote.py
xvirt/plugin_server.py
xvirt/empty/__init__.py
pytest_xvirt-0.3.1.dist-info/METADATA
pytest_xvirt-0.3.1.dist-info/WHEEL
pytest_xvirt-0.3.1.dist-info/entry_points.txt
pytest_xvirt-0.3.1.dist-info/top_level.txt
pytest_xvirt-0.3.1.dist-info/RECORD
