Metadata-Version: 2.1
Name: pytest-xvirt
Version: 0.3.1
Summary: A pytest plugin to virtualize test. For example to transparently running them on a remote box.
Author-email: Simone Giacomelli <simone.giacomelli@gmail.com>, Fabrizio Lamarca <lamarca.fabrizio@gmail.com>
Maintainer-email: Simone Giacomelli <simone.giacomelli@gmail.com>
License: MIT
Project-URL: Homepage, https://github.com/www-py/pytest-xvirt
Keywords: pytest,plugin,virtualize,test,remote,environment,box
Classifier: Development Status :: 4 - Beta
Classifier: Intended Audience :: Developers
Classifier: Framework :: Pytest
Classifier: Topic :: Software Development :: Testing
Classifier: Programming Language :: Python :: 3
Classifier: Programming Language :: Python :: 3.9
Classifier: Programming Language :: Python :: 3.10
Classifier: Programming Language :: Python :: 3.11
Classifier: Programming Language :: Python :: 3.12
Requires-Python: >=3.9
Requires-Dist: pytest>=7.2.2
Provides-Extra: dev
Requires-Dist: build==0.6.0.post1; extra == "dev"
Requires-Dist: twine==3.4.2; extra == "dev"
Requires-Dist: wheel==0.37.0; extra == "dev"
Provides-Extra: pypi
Requires-Dist: twine; extra == "pypi"
